{
  "name" : "instance_{02-00-01}_{06-01}_01",
  "ETA_CONGESTION" : 20.0,
  "ETA_ROUTE" : 4.9999999999999996E-6,
  "SPACE_CAPACITY" : 240,
  "MAX_UNLOAD_FLOWS" : 4,
  "MAX_LOAD_FLOWS" : 4,
  "horizon" : 42,
  "extension" : 18,
  "rows" : 6,
  "cols" : 1,
  "roads" : 6,
  "vessels" : [ {
    "vId" : 0,
    "type" : "small",
    "lengthOfPeriod" : 21,
    "idleTimeSteps" : 18,
    "relativeFeasibleIntervalStart" : 1,
    "relativeFeasibleIntervalDuration" : 20,
    "relativeExpectedIntervalStart" : 14,
    "relativeExpectedIntervalDuration" : 4,
    "vpIds" : [ 0, 1 ]
  }, {
    "vId" : 1,
    "type" : "small",
    "lengthOfPeriod" : 21,
    "idleTimeSteps" : 4,
    "relativeFeasibleIntervalStart" : 1,
    "relativeFeasibleIntervalDuration" : 20,
    "relativeExpectedIntervalStart" : 14,
    "relativeExpectedIntervalDuration" : 4,
    "vpIds" : [ 2, 3 ]
  }, {
    "vId" : 2,
    "type" : "large",
    "lengthOfPeriod" : 42,
    "idleTimeSteps" : 1,
    "relativeFeasibleIntervalStart" : 22,
    "relativeFeasibleIntervalDuration" : 20,
    "relativeExpectedIntervalStart" : 35,
    "relativeExpectedIntervalDuration" : 4,
    "vpIds" : [ 4 ]
  } ],
  "vesselPeriods" : [ {
    "vpId" : 0,
    "vid" : 0,
    "pid" : 0,
    "type" : "small",
    "absolutePeriodStart" : 18,
    "absolutePeriodDuration" : 21,
    "relativeFeasibleIntervalStart" : 1,
    "relativeFeasibleIntervalDuration" : 20,
    "relativeExpectedIntervalStart" : 14,
    "relativeExpectedIntervalDuration" : 4,
    "berthPosition" : 39.834887884769714,
    "earlinessCost" : 3.6297592048475056,
    "tardinessCost" : 2.144941528601471,
    "totalUnloadContainers" : 259,
    "totalLoadContainers" : 264,
    "totalUnloadFlow" : 1,
    "totalLoadFlow" : 1
  }, {
    "vpId" : 1,
    "vid" : 0,
    "pid" : 1,
    "type" : "small",
    "absolutePeriodStart" : 39,
    "absolutePeriodDuration" : 21,
    "relativeFeasibleIntervalStart" : 1,
    "relativeFeasibleIntervalDuration" : 20,
    "relativeExpectedIntervalStart" : 14,
    "relativeExpectedIntervalDuration" : 4,
    "berthPosition" : 92.25063959689298,
    "earlinessCost" : 4.635468957886451,
    "tardinessCost" : 4.842958510286641,
    "totalUnloadContainers" : 545,
    "totalLoadContainers" : 536,
    "totalUnloadFlow" : 2,
    "totalLoadFlow" : 2
  }, {
    "vpId" : 2,
    "vid" : 1,
    "pid" : 0,
    "type" : "small",
    "absolutePeriodStart" : 4,
    "absolutePeriodDuration" : 21,
    "relativeFeasibleIntervalStart" : 1,
    "relativeFeasibleIntervalDuration" : 20,
    "relativeExpectedIntervalStart" : 14,
    "relativeExpectedIntervalDuration" : 4,
    "berthPosition" : 216.11574707913059,
    "earlinessCost" : 2.610944805366087,
    "tardinessCost" : 2.638312216989123,
    "totalUnloadContainers" : 519,
    "totalLoadContainers" : 286,
    "totalUnloadFlow" : 2,
    "totalLoadFlow" : 1
  }, {
    "vpId" : 3,
    "vid" : 1,
    "pid" : 1,
    "type" : "small",
    "absolutePeriodStart" : 25,
    "absolutePeriodDuration" : 21,
    "relativeFeasibleIntervalStart" : 1,
    "relativeFeasibleIntervalDuration" : 20,
    "relativeExpectedIntervalStart" : 14,
    "relativeExpectedIntervalDuration" : 4,
    "berthPosition" : 134.8149171864088,
    "earlinessCost" : 4.216289278697664,
    "tardinessCost" : 5.643801923816332,
    "totalUnloadContainers" : 289,
    "totalLoadContainers" : 503,
    "totalUnloadFlow" : 1,
    "totalLoadFlow" : 2
  }, {
    "vpId" : 4,
    "vid" : 2,
    "pid" : 0,
    "type" : "large",
    "absolutePeriodStart" : 1,
    "absolutePeriodDuration" : 42,
    "relativeFeasibleIntervalStart" : 22,
    "relativeFeasibleIntervalDuration" : 20,
    "relativeExpectedIntervalStart" : 35,
    "relativeExpectedIntervalDuration" : 4,
    "berthPosition" : 145.83846427460279,
    "earlinessCost" : 11.94834949953403,
    "tardinessCost" : 13.65585150405872,
    "totalUnloadContainers" : 491,
    "totalLoadContainers" : 514,
    "totalUnloadFlow" : 2,
    "totalLoadFlow" : 2
  } ],
  "subblocks" : [ {
    "id" : 0,
    "blockId" : 0,
    "rowId" : 0,
    "colId" : 0,
    "slotId" : 0,
    "hLaneId" : 0
  }, {
    "id" : 1,
    "blockId" : 0,
    "rowId" : 0,
    "colId" : 0,
    "slotId" : 1,
    "hLaneId" : 0
  }, {
    "id" : 2,
    "blockId" : 0,
    "rowId" : 0,
    "colId" : 0,
    "slotId" : 2,
    "hLaneId" : 0
  }, {
    "id" : 3,
    "blockId" : 0,
    "rowId" : 0,
    "colId" : 0,
    "slotId" : 3,
    "hLaneId" : 0
  }, {
    "id" : 4,
    "blockId" : 0,
    "rowId" : 0,
    "colId" : 0,
    "slotId" : 4,
    "hLaneId" : 0
  }, {
    "id" : 5,
    "blockId" : 1,
    "rowId" : 1,
    "colId" : 0,
    "slotId" : 0,
    "hLaneId" : 1
  }, {
    "id" : 6,
    "blockId" : 1,
    "rowId" : 1,
    "colId" : 0,
    "slotId" : 1,
    "hLaneId" : 1
  }, {
    "id" : 7,
    "blockId" : 1,
    "rowId" : 1,
    "colId" : 0,
    "slotId" : 2,
    "hLaneId" : 1
  }, {
    "id" : 8,
    "blockId" : 1,
    "rowId" : 1,
    "colId" : 0,
    "slotId" : 3,
    "hLaneId" : 1
  }, {
    "id" : 9,
    "blockId" : 1,
    "rowId" : 1,
    "colId" : 0,
    "slotId" : 4,
    "hLaneId" : 1
  }, {
    "id" : 10,
    "blockId" : 2,
    "rowId" : 2,
    "colId" : 0,
    "slotId" : 0,
    "hLaneId" : 1
  }, {
    "id" : 11,
    "blockId" : 2,
    "rowId" : 2,
    "colId" : 0,
    "slotId" : 1,
    "hLaneId" : 1
  }, {
    "id" : 12,
    "blockId" : 2,
    "rowId" : 2,
    "colId" : 0,
    "slotId" : 2,
    "hLaneId" : 1
  }, {
    "id" : 13,
    "blockId" : 2,
    "rowId" : 2,
    "colId" : 0,
    "slotId" : 3,
    "hLaneId" : 1
  }, {
    "id" : 14,
    "blockId" : 2,
    "rowId" : 2,
    "colId" : 0,
    "slotId" : 4,
    "hLaneId" : 1
  }, {
    "id" : 15,
    "blockId" : 3,
    "rowId" : 3,
    "colId" : 0,
    "slotId" : 0,
    "hLaneId" : 2
  }, {
    "id" : 16,
    "blockId" : 3,
    "rowId" : 3,
    "colId" : 0,
    "slotId" : 1,
    "hLaneId" : 2
  }, {
    "id" : 17,
    "blockId" : 3,
    "rowId" : 3,
    "colId" : 0,
    "slotId" : 2,
    "hLaneId" : 2
  }, {
    "id" : 18,
    "blockId" : 3,
    "rowId" : 3,
    "colId" : 0,
    "slotId" : 3,
    "hLaneId" : 2
  }, {
    "id" : 19,
    "blockId" : 3,
    "rowId" : 3,
    "colId" : 0,
    "slotId" : 4,
    "hLaneId" : 2
  }, {
    "id" : 20,
    "blockId" : 4,
    "rowId" : 4,
    "colId" : 0,
    "slotId" : 0,
    "hLaneId" : 2
  }, {
    "id" : 21,
    "blockId" : 4,
    "rowId" : 4,
    "colId" : 0,
    "slotId" : 1,
    "hLaneId" : 2
  }, {
    "id" : 22,
    "blockId" : 4,
    "rowId" : 4,
    "colId" : 0,
    "slotId" : 2,
    "hLaneId" : 2
  }, {
    "id" : 23,
    "blockId" : 4,
    "rowId" : 4,
    "colId" : 0,
    "slotId" : 3,
    "hLaneId" : 2
  }, {
    "id" : 24,
    "blockId" : 4,
    "rowId" : 4,
    "colId" : 0,
    "slotId" : 4,
    "hLaneId" : 2
  }, {
    "id" : 25,
    "blockId" : 5,
    "rowId" : 5,
    "colId" : 0,
    "slotId" : 0,
    "hLaneId" : 3
  }, {
    "id" : 26,
    "blockId" : 5,
    "rowId" : 5,
    "colId" : 0,
    "slotId" : 1,
    "hLaneId" : 3
  }, {
    "id" : 27,
    "blockId" : 5,
    "rowId" : 5,
    "colId" : 0,
    "slotId" : 2,
    "hLaneId" : 3
  }, {
    "id" : 28,
    "blockId" : 5,
    "rowId" : 5,
    "colId" : 0,
    "slotId" : 3,
    "hLaneId" : 3
  }, {
    "id" : 29,
    "blockId" : 5,
    "rowId" : 5,
    "colId" : 0,
    "slotId" : 4,
    "hLaneId" : 3
  } ],
  "routingInfos" : [ {
    "vpId" : 0,
    "subblockId" : 13,
    "distanceToSubblock" : 219.83488788476973,
    "distanceFromSubblock" : 340.1651121152303,
    "routeToSubblock" : [ 0 ],
    "routeFromSubblock" : [ 1 ]
  }, {
    "vpId" : 0,
    "subblockId" : 24,
    "distanceToSubblock" : 299.8348878847697,
    "distanceFromSubblock" : 320.1651121152303,
    "routeToSubblock" : [ 0, 2 ],
    "routeFromSubblock" : [ 3, 1 ]
  }, {
    "vpId" : 1,
    "subblockId" : 23,
    "distanceToSubblock" : 302.250639596893,
    "distanceFromSubblock" : 317.749360403107,
    "routeToSubblock" : [ 0, 2 ],
    "routeFromSubblock" : [ 3, 1 ]
  }, {
    "vpId" : 0,
    "subblockId" : 16,
    "distanceToSubblock" : 149.83488788476973,
    "distanceFromSubblock" : 470.1651121152303,
    "routeToSubblock" : [ 0, 2 ],
    "routeFromSubblock" : [ 3, 1 ]
  }, {
    "vpId" : 4,
    "subblockId" : 23,
    "distanceToSubblock" : 355.83846427460276,
    "distanceFromSubblock" : 264.16153572539724,
    "routeToSubblock" : [ 0, 2 ],
    "routeFromSubblock" : [ 3, 1 ]
  }, {
    "vpId" : 4,
    "subblockId" : 15,
    "distanceToSubblock" : 205.83846427460279,
    "distanceFromSubblock" : 414.16153572539724,
    "routeToSubblock" : [ 0, 2 ],
    "routeFromSubblock" : [ 3, 1 ]
  }, {
    "vpId" : 3,
    "subblockId" : 13,
    "distanceToSubblock" : 314.8149171864088,
    "distanceFromSubblock" : 245.1850828135912,
    "routeToSubblock" : [ 0 ],
    "routeFromSubblock" : [ 1 ]
  }, {
    "vpId" : 3,
    "subblockId" : 15,
    "distanceToSubblock" : 194.8149171864088,
    "distanceFromSubblock" : 425.1850828135912,
    "routeToSubblock" : [ 0, 2 ],
    "routeFromSubblock" : [ 3, 1 ]
  }, {
    "vpId" : 4,
    "subblockId" : 4,
    "distanceToSubblock" : 345.83846427460276,
    "distanceFromSubblock" : 154.16153572539721,
    "routeToSubblock" : [ ],
    "routeFromSubblock" : [ ]
  }, {
    "vpId" : 4,
    "subblockId" : 26,
    "distanceToSubblock" : 285.83846427460276,
    "distanceFromSubblock" : 394.16153572539724,
    "routeToSubblock" : [ 0, 2, 4 ],
    "routeFromSubblock" : [ 5, 3, 1 ]
  }, {
    "vpId" : 2,
    "subblockId" : 7,
    "distanceToSubblock" : 346.1157470791306,
    "distanceFromSubblock" : 213.88425292086941,
    "routeToSubblock" : [ 0 ],
    "routeFromSubblock" : [ 1 ]
  }, {
    "vpId" : 2,
    "subblockId" : 18,
    "distanceToSubblock" : 426.1157470791306,
    "distanceFromSubblock" : 193.88425292086941,
    "routeToSubblock" : [ 0, 2 ],
    "routeFromSubblock" : [ 3, 1 ]
  }, {
    "vpId" : 3,
    "subblockId" : 25,
    "distanceToSubblock" : 224.8149171864088,
    "distanceFromSubblock" : 455.1850828135912,
    "routeToSubblock" : [ 0, 2, 4 ],
    "routeFromSubblock" : [ 5, 3, 1 ]
  }, {
    "vpId" : 4,
    "subblockId" : 11,
    "distanceToSubblock" : 225.83846427460279,
    "distanceFromSubblock" : 334.16153572539724,
    "routeToSubblock" : [ 0 ],
    "routeFromSubblock" : [ 1 ]
  }, {
    "vpId" : 1,
    "subblockId" : 25,
    "distanceToSubblock" : 182.250639596893,
    "distanceFromSubblock" : 497.749360403107,
    "routeToSubblock" : [ 0, 2, 4 ],
    "routeFromSubblock" : [ 5, 3, 1 ]
  }, {
    "vpId" : 4,
    "subblockId" : 25,
    "distanceToSubblock" : 235.83846427460279,
    "distanceFromSubblock" : 444.16153572539724,
    "routeToSubblock" : [ 0, 2, 4 ],
    "routeFromSubblock" : [ 5, 3, 1 ]
  }, {
    "vpId" : 2,
    "subblockId" : 28,
    "distanceToSubblock" : 456.1157470791306,
    "distanceFromSubblock" : 223.88425292086941,
    "routeToSubblock" : [ 0, 2, 4 ],
    "routeFromSubblock" : [ 5, 3, 1 ]
  }, {
    "vpId" : 2,
    "subblockId" : 11,
    "distanceToSubblock" : 296.1157470791306,
    "distanceFromSubblock" : 263.8842529208694,
    "routeToSubblock" : [ 0 ],
    "routeFromSubblock" : [ 1 ]
  }, {
    "vpId" : 1,
    "subblockId" : 26,
    "distanceToSubblock" : 232.250639596893,
    "distanceFromSubblock" : 447.749360403107,
    "routeToSubblock" : [ 0, 2, 4 ],
    "routeFromSubblock" : [ 5, 3, 1 ]
  }, {
    "vpId" : 0,
    "subblockId" : 6,
    "distanceToSubblock" : 119.83488788476971,
    "distanceFromSubblock" : 440.1651121152303,
    "routeToSubblock" : [ 0 ],
    "routeFromSubblock" : [ 1 ]
  }, {
    "vpId" : 1,
    "subblockId" : 6,
    "distanceToSubblock" : 172.250639596893,
    "distanceFromSubblock" : 387.749360403107,
    "routeToSubblock" : [ 0 ],
    "routeFromSubblock" : [ 1 ]
  }, {
    "vpId" : 1,
    "subblockId" : 13,
    "distanceToSubblock" : 272.250639596893,
    "distanceFromSubblock" : 287.749360403107,
    "routeToSubblock" : [ 0 ],
    "routeFromSubblock" : [ 1 ]
  }, {
    "vpId" : 1,
    "subblockId" : 15,
    "distanceToSubblock" : 152.250639596893,
    "distanceFromSubblock" : 467.749360403107,
    "routeToSubblock" : [ 0, 2 ],
    "routeFromSubblock" : [ 3, 1 ]
  }, {
    "vpId" : 1,
    "subblockId" : 21,
    "distanceToSubblock" : 202.250639596893,
    "distanceFromSubblock" : 417.749360403107,
    "routeToSubblock" : [ 0, 2 ],
    "routeFromSubblock" : [ 3, 1 ]
  }, {
    "vpId" : 4,
    "subblockId" : 17,
    "distanceToSubblock" : 305.83846427460276,
    "distanceFromSubblock" : 314.16153572539724,
    "routeToSubblock" : [ 0, 2 ],
    "routeFromSubblock" : [ 3, 1 ]
  }, {
    "vpId" : 1,
    "subblockId" : 3,
    "distanceToSubblock" : 242.250639596893,
    "distanceFromSubblock" : 257.749360403107,
    "routeToSubblock" : [ ],
    "routeFromSubblock" : [ ]
  }, {
    "vpId" : 2,
    "subblockId" : 26,
    "distanceToSubblock" : 356.1157470791306,
    "distanceFromSubblock" : 323.8842529208694,
    "routeToSubblock" : [ 0, 2, 4 ],
    "routeFromSubblock" : [ 5, 3, 1 ]
  }, {
    "vpId" : 2,
    "subblockId" : 14,
    "distanceToSubblock" : 446.1157470791306,
    "distanceFromSubblock" : 113.88425292086941,
    "routeToSubblock" : [ 0 ],
    "routeFromSubblock" : [ 1 ]
  }, {
    "vpId" : 3,
    "subblockId" : 9,
    "distanceToSubblock" : 364.8149171864088,
    "distanceFromSubblock" : 195.1850828135912,
    "routeToSubblock" : [ 0 ],
    "routeFromSubblock" : [ 1 ]
  }, {
    "vpId" : 0,
    "subblockId" : 20,
    "distanceToSubblock" : 99.83488788476971,
    "distanceFromSubblock" : 520.1651121152303,
    "routeToSubblock" : [ 0, 2 ],
    "routeFromSubblock" : [ 3, 1 ]
  }, {
    "vpId" : 3,
    "subblockId" : 2,
    "distanceToSubblock" : 234.8149171864088,
    "distanceFromSubblock" : 265.1850828135912,
    "routeToSubblock" : [ ],
    "routeFromSubblock" : [ ]
  }, {
    "vpId" : 4,
    "subblockId" : 13,
    "distanceToSubblock" : 325.83846427460276,
    "distanceFromSubblock" : 234.16153572539721,
    "routeToSubblock" : [ 0 ],
    "routeFromSubblock" : [ 1 ]
  }, {
    "vpId" : 1,
    "subblockId" : 10,
    "distanceToSubblock" : 122.25063959689298,
    "distanceFromSubblock" : 437.749360403107,
    "routeToSubblock" : [ 0 ],
    "routeFromSubblock" : [ 1 ]
  }, {
    "vpId" : 2,
    "subblockId" : 2,
    "distanceToSubblock" : 316.1157470791306,
    "distanceFromSubblock" : 183.88425292086941,
    "routeToSubblock" : [ ],
    "routeFromSubblock" : [ ]
  }, {
    "vpId" : 3,
    "subblockId" : 24,
    "distanceToSubblock" : 394.8149171864088,
    "distanceFromSubblock" : 225.1850828135912,
    "routeToSubblock" : [ 0, 2 ],
    "routeFromSubblock" : [ 3, 1 ]
  }, {
    "vpId" : 3,
    "subblockId" : 5,
    "distanceToSubblock" : 164.8149171864088,
    "distanceFromSubblock" : 395.1850828135912,
    "routeToSubblock" : [ 0 ],
    "routeFromSubblock" : [ 1 ]
  }, {
    "vpId" : 0,
    "subblockId" : 2,
    "distanceToSubblock" : 139.83488788476973,
    "distanceFromSubblock" : 360.1651121152303,
    "routeToSubblock" : [ ],
    "routeFromSubblock" : [ ]
  }, {
    "vpId" : 3,
    "subblockId" : 4,
    "distanceToSubblock" : 334.8149171864088,
    "distanceFromSubblock" : 165.1850828135912,
    "routeToSubblock" : [ ],
    "routeFromSubblock" : [ ]
  }, {
    "vpId" : 1,
    "subblockId" : 14,
    "distanceToSubblock" : 322.250639596893,
    "distanceFromSubblock" : 237.749360403107,
    "routeToSubblock" : [ 0 ],
    "routeFromSubblock" : [ 1 ]
  }, {
    "vpId" : 2,
    "subblockId" : 0,
    "distanceToSubblock" : 216.11574707913059,
    "distanceFromSubblock" : 283.8842529208694,
    "routeToSubblock" : [ ],
    "routeFromSubblock" : [ ]
  }, {
    "vpId" : 3,
    "subblockId" : 11,
    "distanceToSubblock" : 214.8149171864088,
    "distanceFromSubblock" : 345.1850828135912,
    "routeToSubblock" : [ 0 ],
    "routeFromSubblock" : [ 1 ]
  }, {
    "vpId" : 4,
    "subblockId" : 21,
    "distanceToSubblock" : 255.83846427460279,
    "distanceFromSubblock" : 364.16153572539724,
    "routeToSubblock" : [ 0, 2 ],
    "routeFromSubblock" : [ 3, 1 ]
  }, {
    "vpId" : 2,
    "subblockId" : 6,
    "distanceToSubblock" : 296.1157470791306,
    "distanceFromSubblock" : 263.8842529208694,
    "routeToSubblock" : [ 0 ],
    "routeFromSubblock" : [ 1 ]
  }, {
    "vpId" : 2,
    "subblockId" : 16,
    "distanceToSubblock" : 326.1157470791306,
    "distanceFromSubblock" : 293.8842529208694,
    "routeToSubblock" : [ 0, 2 ],
    "routeFromSubblock" : [ 3, 1 ]
  }, {
    "vpId" : 0,
    "subblockId" : 26,
    "distanceToSubblock" : 179.83488788476973,
    "distanceFromSubblock" : 500.1651121152303,
    "routeToSubblock" : [ 0, 2, 4 ],
    "routeFromSubblock" : [ 5, 3, 1 ]
  }, {
    "vpId" : 2,
    "subblockId" : 10,
    "distanceToSubblock" : 246.11574707913059,
    "distanceFromSubblock" : 313.8842529208694,
    "routeToSubblock" : [ 0 ],
    "routeFromSubblock" : [ 1 ]
  }, {
    "vpId" : 2,
    "subblockId" : 23,
    "distanceToSubblock" : 426.1157470791306,
    "distanceFromSubblock" : 193.88425292086941,
    "routeToSubblock" : [ 0, 2 ],
    "routeFromSubblock" : [ 3, 1 ]
  }, {
    "vpId" : 0,
    "subblockId" : 18,
    "distanceToSubblock" : 249.83488788476973,
    "distanceFromSubblock" : 370.1651121152303,
    "routeToSubblock" : [ 0, 2 ],
    "routeFromSubblock" : [ 3, 1 ]
  }, {
    "vpId" : 1,
    "subblockId" : 0,
    "distanceToSubblock" : 92.25063959689298,
    "distanceFromSubblock" : 407.749360403107,
    "routeToSubblock" : [ ],
    "routeFromSubblock" : [ ]
  }, {
    "vpId" : 2,
    "subblockId" : 13,
    "distanceToSubblock" : 396.1157470791306,
    "distanceFromSubblock" : 163.88425292086941,
    "routeToSubblock" : [ 0 ],
    "routeFromSubblock" : [ 1 ]
  }, {
    "vpId" : 0,
    "subblockId" : 19,
    "distanceToSubblock" : 299.8348878847697,
    "distanceFromSubblock" : 320.1651121152303,
    "routeToSubblock" : [ 0, 2 ],
    "routeFromSubblock" : [ 3, 1 ]
  }, {
    "vpId" : 4,
    "subblockId" : 22,
    "distanceToSubblock" : 305.83846427460276,
    "distanceFromSubblock" : 314.16153572539724,
    "routeToSubblock" : [ 0, 2 ],
    "routeFromSubblock" : [ 3, 1 ]
  }, {
    "vpId" : 1,
    "subblockId" : 11,
    "distanceToSubblock" : 172.250639596893,
    "distanceFromSubblock" : 387.749360403107,
    "routeToSubblock" : [ 0 ],
    "routeFromSubblock" : [ 1 ]
  }, {
    "vpId" : 4,
    "subblockId" : 7,
    "distanceToSubblock" : 275.83846427460276,
    "distanceFromSubblock" : 284.16153572539724,
    "routeToSubblock" : [ 0 ],
    "routeFromSubblock" : [ 1 ]
  }, {
    "vpId" : 0,
    "subblockId" : 25,
    "distanceToSubblock" : 129.83488788476973,
    "distanceFromSubblock" : 550.1651121152303,
    "routeToSubblock" : [ 0, 2, 4 ],
    "routeFromSubblock" : [ 5, 3, 1 ]
  }, {
    "vpId" : 2,
    "subblockId" : 9,
    "distanceToSubblock" : 446.1157470791306,
    "distanceFromSubblock" : 113.88425292086941,
    "routeToSubblock" : [ 0 ],
    "routeFromSubblock" : [ 1 ]
  }, {
    "vpId" : 1,
    "subblockId" : 5,
    "distanceToSubblock" : 122.25063959689298,
    "distanceFromSubblock" : 437.749360403107,
    "routeToSubblock" : [ 0 ],
    "routeFromSubblock" : [ 1 ]
  }, {
    "vpId" : 0,
    "subblockId" : 23,
    "distanceToSubblock" : 249.83488788476973,
    "distanceFromSubblock" : 370.1651121152303,
    "routeToSubblock" : [ 0, 2 ],
    "routeFromSubblock" : [ 3, 1 ]
  }, {
    "vpId" : 4,
    "subblockId" : 8,
    "distanceToSubblock" : 325.83846427460276,
    "distanceFromSubblock" : 234.16153572539721,
    "routeToSubblock" : [ 0 ],
    "routeFromSubblock" : [ 1 ]
  }, {
    "vpId" : 1,
    "subblockId" : 28,
    "distanceToSubblock" : 332.250639596893,
    "distanceFromSubblock" : 347.749360403107,
    "routeToSubblock" : [ 0, 2, 4 ],
    "routeFromSubblock" : [ 5, 3, 1 ]
  }, {
    "vpId" : 2,
    "subblockId" : 27,
    "distanceToSubblock" : 406.1157470791306,
    "distanceFromSubblock" : 273.8842529208694,
    "routeToSubblock" : [ 0, 2, 4 ],
    "routeFromSubblock" : [ 5, 3, 1 ]
  }, {
    "vpId" : 4,
    "subblockId" : 6,
    "distanceToSubblock" : 225.83846427460279,
    "distanceFromSubblock" : 334.16153572539724,
    "routeToSubblock" : [ 0 ],
    "routeFromSubblock" : [ 1 ]
  }, {
    "vpId" : 4,
    "subblockId" : 27,
    "distanceToSubblock" : 335.83846427460276,
    "distanceFromSubblock" : 344.16153572539724,
    "routeToSubblock" : [ 0, 2, 4 ],
    "routeFromSubblock" : [ 5, 3, 1 ]
  }, {
    "vpId" : 3,
    "subblockId" : 12,
    "distanceToSubblock" : 264.8149171864088,
    "distanceFromSubblock" : 295.1850828135912,
    "routeToSubblock" : [ 0 ],
    "routeFromSubblock" : [ 1 ]
  }, {
    "vpId" : 1,
    "subblockId" : 4,
    "distanceToSubblock" : 292.250639596893,
    "distanceFromSubblock" : 207.749360403107,
    "routeToSubblock" : [ ],
    "routeFromSubblock" : [ ]
  }, {
    "vpId" : 0,
    "subblockId" : 9,
    "distanceToSubblock" : 269.8348878847697,
    "distanceFromSubblock" : 290.1651121152303,
    "routeToSubblock" : [ 0 ],
    "routeFromSubblock" : [ 1 ]
  }, {
    "vpId" : 0,
    "subblockId" : 0,
    "distanceToSubblock" : 39.834887884769714,
    "distanceFromSubblock" : 460.1651121152303,
    "routeToSubblock" : [ ],
    "routeFromSubblock" : [ ]
  }, {
    "vpId" : 4,
    "subblockId" : 16,
    "distanceToSubblock" : 255.83846427460279,
    "distanceFromSubblock" : 364.16153572539724,
    "routeToSubblock" : [ 0, 2 ],
    "routeFromSubblock" : [ 3, 1 ]
  }, {
    "vpId" : 1,
    "subblockId" : 7,
    "distanceToSubblock" : 222.250639596893,
    "distanceFromSubblock" : 337.749360403107,
    "routeToSubblock" : [ 0 ],
    "routeFromSubblock" : [ 1 ]
  }, {
    "vpId" : 0,
    "subblockId" : 4,
    "distanceToSubblock" : 239.83488788476973,
    "distanceFromSubblock" : 260.1651121152303,
    "routeToSubblock" : [ ],
    "routeFromSubblock" : [ ]
  }, {
    "vpId" : 1,
    "subblockId" : 9,
    "distanceToSubblock" : 322.250639596893,
    "distanceFromSubblock" : 237.749360403107,
    "routeToSubblock" : [ 0 ],
    "routeFromSubblock" : [ 1 ]
  }, {
    "vpId" : 2,
    "subblockId" : 17,
    "distanceToSubblock" : 376.1157470791306,
    "distanceFromSubblock" : 243.88425292086941,
    "routeToSubblock" : [ 0, 2 ],
    "routeFromSubblock" : [ 3, 1 ]
  }, {
    "vpId" : 2,
    "subblockId" : 21,
    "distanceToSubblock" : 326.1157470791306,
    "distanceFromSubblock" : 293.8842529208694,
    "routeToSubblock" : [ 0, 2 ],
    "routeFromSubblock" : [ 3, 1 ]
  }, {
    "vpId" : 4,
    "subblockId" : 10,
    "distanceToSubblock" : 175.83846427460279,
    "distanceFromSubblock" : 384.16153572539724,
    "routeToSubblock" : [ 0 ],
    "routeFromSubblock" : [ 1 ]
  }, {
    "vpId" : 2,
    "subblockId" : 8,
    "distanceToSubblock" : 396.1157470791306,
    "distanceFromSubblock" : 163.88425292086941,
    "routeToSubblock" : [ 0 ],
    "routeFromSubblock" : [ 1 ]
  }, {
    "vpId" : 4,
    "subblockId" : 2,
    "distanceToSubblock" : 245.83846427460279,
    "distanceFromSubblock" : 254.16153572539721,
    "routeToSubblock" : [ ],
    "routeFromSubblock" : [ ]
  }, {
    "vpId" : 3,
    "subblockId" : 1,
    "distanceToSubblock" : 184.8149171864088,
    "distanceFromSubblock" : 315.1850828135912,
    "routeToSubblock" : [ ],
    "routeFromSubblock" : [ ]
  }, {
    "vpId" : 1,
    "subblockId" : 27,
    "distanceToSubblock" : 282.250639596893,
    "distanceFromSubblock" : 397.749360403107,
    "routeToSubblock" : [ 0, 2, 4 ],
    "routeFromSubblock" : [ 5, 3, 1 ]
  }, {
    "vpId" : 2,
    "subblockId" : 3,
    "distanceToSubblock" : 366.1157470791306,
    "distanceFromSubblock" : 133.88425292086941,
    "routeToSubblock" : [ ],
    "routeFromSubblock" : [ ]
  }, {
    "vpId" : 4,
    "subblockId" : 3,
    "distanceToSubblock" : 295.83846427460276,
    "distanceFromSubblock" : 204.16153572539721,
    "routeToSubblock" : [ ],
    "routeFromSubblock" : [ ]
  }, {
    "vpId" : 1,
    "subblockId" : 1,
    "distanceToSubblock" : 142.250639596893,
    "distanceFromSubblock" : 357.749360403107,
    "routeToSubblock" : [ ],
    "routeFromSubblock" : [ ]
  }, {
    "vpId" : 2,
    "subblockId" : 15,
    "distanceToSubblock" : 276.1157470791306,
    "distanceFromSubblock" : 343.8842529208694,
    "routeToSubblock" : [ 0, 2 ],
    "routeFromSubblock" : [ 3, 1 ]
  }, {
    "vpId" : 0,
    "subblockId" : 7,
    "distanceToSubblock" : 169.83488788476973,
    "distanceFromSubblock" : 390.1651121152303,
    "routeToSubblock" : [ 0 ],
    "routeFromSubblock" : [ 1 ]
  }, {
    "vpId" : 1,
    "subblockId" : 19,
    "distanceToSubblock" : 352.250639596893,
    "distanceFromSubblock" : 267.749360403107,
    "routeToSubblock" : [ 0, 2 ],
    "routeFromSubblock" : [ 3, 1 ]
  }, {
    "vpId" : 3,
    "subblockId" : 14,
    "distanceToSubblock" : 364.8149171864088,
    "distanceFromSubblock" : 195.1850828135912,
    "routeToSubblock" : [ 0 ],
    "routeFromSubblock" : [ 1 ]
  }, {
    "vpId" : 2,
    "subblockId" : 29,
    "distanceToSubblock" : 506.1157470791306,
    "distanceFromSubblock" : 173.88425292086941,
    "routeToSubblock" : [ 0, 2, 4 ],
    "routeFromSubblock" : [ 5, 3, 1 ]
  }, {
    "vpId" : 2,
    "subblockId" : 5,
    "distanceToSubblock" : 246.11574707913059,
    "distanceFromSubblock" : 313.8842529208694,
    "routeToSubblock" : [ 0 ],
    "routeFromSubblock" : [ 1 ]
  }, {
    "vpId" : 4,
    "subblockId" : 1,
    "distanceToSubblock" : 195.83846427460279,
    "distanceFromSubblock" : 304.16153572539724,
    "routeToSubblock" : [ ],
    "routeFromSubblock" : [ ]
  }, {
    "vpId" : 4,
    "subblockId" : 12,
    "distanceToSubblock" : 275.83846427460276,
    "distanceFromSubblock" : 284.16153572539724,
    "routeToSubblock" : [ 0 ],
    "routeFromSubblock" : [ 1 ]
  }, {
    "vpId" : 1,
    "subblockId" : 20,
    "distanceToSubblock" : 152.250639596893,
    "distanceFromSubblock" : 467.749360403107,
    "routeToSubblock" : [ 0, 2 ],
    "routeFromSubblock" : [ 3, 1 ]
  }, {
    "vpId" : 0,
    "subblockId" : 22,
    "distanceToSubblock" : 199.83488788476973,
    "distanceFromSubblock" : 420.1651121152303,
    "routeToSubblock" : [ 0, 2 ],
    "routeFromSubblock" : [ 3, 1 ]
  }, {
    "vpId" : 4,
    "subblockId" : 28,
    "distanceToSubblock" : 385.83846427460276,
    "distanceFromSubblock" : 294.16153572539724,
    "routeToSubblock" : [ 0, 2, 4 ],
    "routeFromSubblock" : [ 5, 3, 1 ]
  }, {
    "vpId" : 1,
    "subblockId" : 16,
    "distanceToSubblock" : 202.250639596893,
    "distanceFromSubblock" : 417.749360403107,
    "routeToSubblock" : [ 0, 2 ],
    "routeFromSubblock" : [ 3, 1 ]
  }, {
    "vpId" : 3,
    "subblockId" : 0,
    "distanceToSubblock" : 134.8149171864088,
    "distanceFromSubblock" : 365.1850828135912,
    "routeToSubblock" : [ ],
    "routeFromSubblock" : [ ]
  }, {
    "vpId" : 0,
    "subblockId" : 14,
    "distanceToSubblock" : 269.8348878847697,
    "distanceFromSubblock" : 290.1651121152303,
    "routeToSubblock" : [ 0 ],
    "routeFromSubblock" : [ 1 ]
  }, {
    "vpId" : 4,
    "subblockId" : 19,
    "distanceToSubblock" : 405.83846427460276,
    "distanceFromSubblock" : 214.16153572539721,
    "routeToSubblock" : [ 0, 2 ],
    "routeFromSubblock" : [ 3, 1 ]
  }, {
    "vpId" : 3,
    "subblockId" : 21,
    "distanceToSubblock" : 244.8149171864088,
    "distanceFromSubblock" : 375.1850828135912,
    "routeToSubblock" : [ 0, 2 ],
    "routeFromSubblock" : [ 3, 1 ]
  }, {
    "vpId" : 0,
    "subblockId" : 27,
    "distanceToSubblock" : 229.83488788476973,
    "distanceFromSubblock" : 450.1651121152303,
    "routeToSubblock" : [ 0, 2, 4 ],
    "routeFromSubblock" : [ 5, 3, 1 ]
  }, {
    "vpId" : 2,
    "subblockId" : 19,
    "distanceToSubblock" : 476.1157470791306,
    "distanceFromSubblock" : 143.88425292086941,
    "routeToSubblock" : [ 0, 2 ],
    "routeFromSubblock" : [ 3, 1 ]
  }, {
    "vpId" : 1,
    "subblockId" : 2,
    "distanceToSubblock" : 192.250639596893,
    "distanceFromSubblock" : 307.749360403107,
    "routeToSubblock" : [ ],
    "routeFromSubblock" : [ ]
  }, {
    "vpId" : 2,
    "subblockId" : 20,
    "distanceToSubblock" : 276.1157470791306,
    "distanceFromSubblock" : 343.8842529208694,
    "routeToSubblock" : [ 0, 2 ],
    "routeFromSubblock" : [ 3, 1 ]
  }, {
    "vpId" : 3,
    "subblockId" : 28,
    "distanceToSubblock" : 374.8149171864088,
    "distanceFromSubblock" : 305.1850828135912,
    "routeToSubblock" : [ 0, 2, 4 ],
    "routeFromSubblock" : [ 5, 3, 1 ]
  }, {
    "vpId" : 3,
    "subblockId" : 18,
    "distanceToSubblock" : 344.8149171864088,
    "distanceFromSubblock" : 275.1850828135912,
    "routeToSubblock" : [ 0, 2 ],
    "routeFromSubblock" : [ 3, 1 ]
  }, {
    "vpId" : 4,
    "subblockId" : 14,
    "distanceToSubblock" : 375.83846427460276,
    "distanceFromSubblock" : 184.16153572539721,
    "routeToSubblock" : [ 0 ],
    "routeFromSubblock" : [ 1 ]
  }, {
    "vpId" : 2,
    "subblockId" : 1,
    "distanceToSubblock" : 266.1157470791306,
    "distanceFromSubblock" : 233.88425292086941,
    "routeToSubblock" : [ ],
    "routeFromSubblock" : [ ]
  }, {
    "vpId" : 3,
    "subblockId" : 6,
    "distanceToSubblock" : 214.8149171864088,
    "distanceFromSubblock" : 345.1850828135912,
    "routeToSubblock" : [ 0 ],
    "routeFromSubblock" : [ 1 ]
  }, {
    "vpId" : 3,
    "subblockId" : 7,
    "distanceToSubblock" : 264.8149171864088,
    "distanceFromSubblock" : 295.1850828135912,
    "routeToSubblock" : [ 0 ],
    "routeFromSubblock" : [ 1 ]
  }, {
    "vpId" : 0,
    "subblockId" : 1,
    "distanceToSubblock" : 89.83488788476971,
    "distanceFromSubblock" : 410.1651121152303,
    "routeToSubblock" : [ ],
    "routeFromSubblock" : [ ]
  }, {
    "vpId" : 1,
    "subblockId" : 18,
    "distanceToSubblock" : 302.250639596893,
    "distanceFromSubblock" : 317.749360403107,
    "routeToSubblock" : [ 0, 2 ],
    "routeFromSubblock" : [ 3, 1 ]
  }, {
    "vpId" : 4,
    "subblockId" : 18,
    "distanceToSubblock" : 355.83846427460276,
    "distanceFromSubblock" : 264.16153572539724,
    "routeToSubblock" : [ 0, 2 ],
    "routeFromSubblock" : [ 3, 1 ]
  }, {
    "vpId" : 2,
    "subblockId" : 25,
    "distanceToSubblock" : 306.1157470791306,
    "distanceFromSubblock" : 373.8842529208694,
    "routeToSubblock" : [ 0, 2, 4 ],
    "routeFromSubblock" : [ 5, 3, 1 ]
  }, {
    "vpId" : 3,
    "subblockId" : 27,
    "distanceToSubblock" : 324.8149171864088,
    "distanceFromSubblock" : 355.1850828135912,
    "routeToSubblock" : [ 0, 2, 4 ],
    "routeFromSubblock" : [ 5, 3, 1 ]
  }, {
    "vpId" : 0,
    "subblockId" : 29,
    "distanceToSubblock" : 329.8348878847697,
    "distanceFromSubblock" : 350.1651121152303,
    "routeToSubblock" : [ 0, 2, 4 ],
    "routeFromSubblock" : [ 5, 3, 1 ]
  }, {
    "vpId" : 1,
    "subblockId" : 24,
    "distanceToSubblock" : 352.250639596893,
    "distanceFromSubblock" : 267.749360403107,
    "routeToSubblock" : [ 0, 2 ],
    "routeFromSubblock" : [ 3, 1 ]
  }, {
    "vpId" : 3,
    "subblockId" : 8,
    "distanceToSubblock" : 314.8149171864088,
    "distanceFromSubblock" : 245.1850828135912,
    "routeToSubblock" : [ 0 ],
    "routeFromSubblock" : [ 1 ]
  }, {
    "vpId" : 3,
    "subblockId" : 17,
    "distanceToSubblock" : 294.8149171864088,
    "distanceFromSubblock" : 325.1850828135912,
    "routeToSubblock" : [ 0, 2 ],
    "routeFromSubblock" : [ 3, 1 ]
  }, {
    "vpId" : 0,
    "subblockId" : 28,
    "distanceToSubblock" : 279.8348878847697,
    "distanceFromSubblock" : 400.1651121152303,
    "routeToSubblock" : [ 0, 2, 4 ],
    "routeFromSubblock" : [ 5, 3, 1 ]
  }, {
    "vpId" : 0,
    "subblockId" : 8,
    "distanceToSubblock" : 219.83488788476973,
    "distanceFromSubblock" : 340.1651121152303,
    "routeToSubblock" : [ 0 ],
    "routeFromSubblock" : [ 1 ]
  }, {
    "vpId" : 2,
    "subblockId" : 22,
    "distanceToSubblock" : 376.1157470791306,
    "distanceFromSubblock" : 243.88425292086941,
    "routeToSubblock" : [ 0, 2 ],
    "routeFromSubblock" : [ 3, 1 ]
  }, {
    "vpId" : 3,
    "subblockId" : 10,
    "distanceToSubblock" : 164.8149171864088,
    "distanceFromSubblock" : 395.1850828135912,
    "routeToSubblock" : [ 0 ],
    "routeFromSubblock" : [ 1 ]
  }, {
    "vpId" : 4,
    "subblockId" : 5,
    "distanceToSubblock" : 175.83846427460279,
    "distanceFromSubblock" : 384.16153572539724,
    "routeToSubblock" : [ 0 ],
    "routeFromSubblock" : [ 1 ]
  }, {
    "vpId" : 0,
    "subblockId" : 5,
    "distanceToSubblock" : 69.83488788476971,
    "distanceFromSubblock" : 490.1651121152303,
    "routeToSubblock" : [ 0 ],
    "routeFromSubblock" : [ 1 ]
  }, {
    "vpId" : 2,
    "subblockId" : 4,
    "distanceToSubblock" : 416.1157470791306,
    "distanceFromSubblock" : 83.88425292086941,
    "routeToSubblock" : [ ],
    "routeFromSubblock" : [ ]
  }, {
    "vpId" : 2,
    "subblockId" : 12,
    "distanceToSubblock" : 346.1157470791306,
    "distanceFromSubblock" : 213.88425292086941,
    "routeToSubblock" : [ 0 ],
    "routeFromSubblock" : [ 1 ]
  }, {
    "vpId" : 1,
    "subblockId" : 22,
    "distanceToSubblock" : 252.250639596893,
    "distanceFromSubblock" : 367.749360403107,
    "routeToSubblock" : [ 0, 2 ],
    "routeFromSubblock" : [ 3, 1 ]
  }, {
    "vpId" : 3,
    "subblockId" : 20,
    "distanceToSubblock" : 194.8149171864088,
    "distanceFromSubblock" : 425.1850828135912,
    "routeToSubblock" : [ 0, 2 ],
    "routeFromSubblock" : [ 3, 1 ]
  }, {
    "vpId" : 0,
    "subblockId" : 3,
    "distanceToSubblock" : 189.83488788476973,
    "distanceFromSubblock" : 310.1651121152303,
    "routeToSubblock" : [ ],
    "routeFromSubblock" : [ ]
  }, {
    "vpId" : 4,
    "subblockId" : 20,
    "distanceToSubblock" : 205.83846427460279,
    "distanceFromSubblock" : 414.16153572539724,
    "routeToSubblock" : [ 0, 2 ],
    "routeFromSubblock" : [ 3, 1 ]
  }, {
    "vpId" : 0,
    "subblockId" : 21,
    "distanceToSubblock" : 149.83488788476973,
    "distanceFromSubblock" : 470.1651121152303,
    "routeToSubblock" : [ 0, 2 ],
    "routeFromSubblock" : [ 3, 1 ]
  }, {
    "vpId" : 2,
    "subblockId" : 24,
    "distanceToSubblock" : 476.1157470791306,
    "distanceFromSubblock" : 143.88425292086941,
    "routeToSubblock" : [ 0, 2 ],
    "routeFromSubblock" : [ 3, 1 ]
  }, {
    "vpId" : 3,
    "subblockId" : 26,
    "distanceToSubblock" : 274.8149171864088,
    "distanceFromSubblock" : 405.1850828135912,
    "routeToSubblock" : [ 0, 2, 4 ],
    "routeFromSubblock" : [ 5, 3, 1 ]
  }, {
    "vpId" : 3,
    "subblockId" : 16,
    "distanceToSubblock" : 244.8149171864088,
    "distanceFromSubblock" : 375.1850828135912,
    "routeToSubblock" : [ 0, 2 ],
    "routeFromSubblock" : [ 3, 1 ]
  }, {
    "vpId" : 1,
    "subblockId" : 8,
    "distanceToSubblock" : 272.250639596893,
    "distanceFromSubblock" : 287.749360403107,
    "routeToSubblock" : [ 0 ],
    "routeFromSubblock" : [ 1 ]
  }, {
    "vpId" : 0,
    "subblockId" : 11,
    "distanceToSubblock" : 119.83488788476971,
    "distanceFromSubblock" : 440.1651121152303,
    "routeToSubblock" : [ 0 ],
    "routeFromSubblock" : [ 1 ]
  }, {
    "vpId" : 4,
    "subblockId" : 24,
    "distanceToSubblock" : 405.83846427460276,
    "distanceFromSubblock" : 214.16153572539721,
    "routeToSubblock" : [ 0, 2 ],
    "routeFromSubblock" : [ 3, 1 ]
  }, {
    "vpId" : 0,
    "subblockId" : 17,
    "distanceToSubblock" : 199.83488788476973,
    "distanceFromSubblock" : 420.1651121152303,
    "routeToSubblock" : [ 0, 2 ],
    "routeFromSubblock" : [ 3, 1 ]
  }, {
    "vpId" : 4,
    "subblockId" : 0,
    "distanceToSubblock" : 145.83846427460279,
    "distanceFromSubblock" : 354.16153572539724,
    "routeToSubblock" : [ ],
    "routeFromSubblock" : [ ]
  }, {
    "vpId" : 0,
    "subblockId" : 12,
    "distanceToSubblock" : 169.83488788476973,
    "distanceFromSubblock" : 390.1651121152303,
    "routeToSubblock" : [ 0 ],
    "routeFromSubblock" : [ 1 ]
  }, {
    "vpId" : 3,
    "subblockId" : 23,
    "distanceToSubblock" : 344.8149171864088,
    "distanceFromSubblock" : 275.1850828135912,
    "routeToSubblock" : [ 0, 2 ],
    "routeFromSubblock" : [ 3, 1 ]
  }, {
    "vpId" : 1,
    "subblockId" : 17,
    "distanceToSubblock" : 252.250639596893,
    "distanceFromSubblock" : 367.749360403107,
    "routeToSubblock" : [ 0, 2 ],
    "routeFromSubblock" : [ 3, 1 ]
  }, {
    "vpId" : 3,
    "subblockId" : 3,
    "distanceToSubblock" : 284.8149171864088,
    "distanceFromSubblock" : 215.1850828135912,
    "routeToSubblock" : [ ],
    "routeFromSubblock" : [ ]
  }, {
    "vpId" : 0,
    "subblockId" : 15,
    "distanceToSubblock" : 99.83488788476971,
    "distanceFromSubblock" : 520.1651121152303,
    "routeToSubblock" : [ 0, 2 ],
    "routeFromSubblock" : [ 3, 1 ]
  }, {
    "vpId" : 3,
    "subblockId" : 19,
    "distanceToSubblock" : 394.8149171864088,
    "distanceFromSubblock" : 225.1850828135912,
    "routeToSubblock" : [ 0, 2 ],
    "routeFromSubblock" : [ 3, 1 ]
  }, {
    "vpId" : 0,
    "subblockId" : 10,
    "distanceToSubblock" : 69.83488788476971,
    "distanceFromSubblock" : 490.1651121152303,
    "routeToSubblock" : [ 0 ],
    "routeFromSubblock" : [ 1 ]
  }, {
    "vpId" : 3,
    "subblockId" : 22,
    "distanceToSubblock" : 294.8149171864088,
    "distanceFromSubblock" : 325.1850828135912,
    "routeToSubblock" : [ 0, 2 ],
    "routeFromSubblock" : [ 3, 1 ]
  }, {
    "vpId" : 3,
    "subblockId" : 29,
    "distanceToSubblock" : 424.8149171864088,
    "distanceFromSubblock" : 255.1850828135912,
    "routeToSubblock" : [ 0, 2, 4 ],
    "routeFromSubblock" : [ 5, 3, 1 ]
  }, {
    "vpId" : 4,
    "subblockId" : 29,
    "distanceToSubblock" : 435.83846427460276,
    "distanceFromSubblock" : 244.16153572539721,
    "routeToSubblock" : [ 0, 2, 4 ],
    "routeFromSubblock" : [ 5, 3, 1 ]
  }, {
    "vpId" : 4,
    "subblockId" : 9,
    "distanceToSubblock" : 375.83846427460276,
    "distanceFromSubblock" : 184.16153572539721,
    "routeToSubblock" : [ 0 ],
    "routeFromSubblock" : [ 1 ]
  }, {
    "vpId" : 1,
    "subblockId" : 12,
    "distanceToSubblock" : 222.250639596893,
    "distanceFromSubblock" : 337.749360403107,
    "routeToSubblock" : [ 0 ],
    "routeFromSubblock" : [ 1 ]
  }, {
    "vpId" : 1,
    "subblockId" : 29,
    "distanceToSubblock" : 382.250639596893,
    "distanceFromSubblock" : 297.749360403107,
    "routeToSubblock" : [ 0, 2, 4 ],
    "routeFromSubblock" : [ 5, 3, 1 ]
  } ],
  "transshipmentInfos" : [ {
    "srcVpId" : 0,
    "dstVpId" : 3,
    "containers" : 259
  }, {
    "srcVpId" : 1,
    "dstVpId" : 4,
    "containers" : 259
  }, {
    "srcVpId" : 3,
    "dstVpId" : 1,
    "containers" : 289
  }, {
    "srcVpId" : 4,
    "dstVpId" : 3,
    "containers" : 244
  }, {
    "srcVpId" : 2,
    "dstVpId" : 0,
    "containers" : 264
  }, {
    "srcVpId" : 4,
    "dstVpId" : 1,
    "containers" : 247
  }, {
    "srcVpId" : 1,
    "dstVpId" : 2,
    "containers" : 286
  }, {
    "srcVpId" : 2,
    "dstVpId" : 4,
    "containers" : 255
  } ]
}